humanfriendly/__init__.py
humanfriendly/case.py
humanfriendly/cli.py
humanfriendly/compat.py
humanfriendly/decorators.py
humanfriendly/deprecation.py
humanfriendly/prompts.py
humanfriendly/sphinx.py
humanfriendly/tables.py
humanfriendly/testing.py
humanfriendly/tests.py
humanfriendly/text.py
humanfriendly/usage.py
humanfriendly/terminal/__init__.py
humanfriendly/terminal/html.py
humanfriendly/terminal/spinners.py
humanfriendly-9.2.dist-info/LICENSE.txt
humanfriendly-9.2.dist-info/METADATA
humanfriendly-9.2.dist-info/WHEEL
humanfriendly-9.2.dist-info/entry_points.txt
humanfriendly-9.2.dist-info/top_level.txt
humanfriendly-9.2.dist-info/RECORD
